{"BaseModel.76595b26-6ee8-42fc-99f7-5a4d7144a926": {"id": "76595b26-6ee8-42fc-99f7-5a4d7144a926", "created_at": "2023-07-21T02:39:26.940422", "updated_at": "2023-07-21T02:39:32.504604", "__class__": "BaseModel"}, "BaseModel.0a2d1786-04fb-41bf-995d-e5af2fd3cdd7": {"id": "0a2d1786-04fb-41bf-995d-e5af2fd3cdd7", "created_at": "2023-07-21T02:41:13.087248", "updated_at": "2023-07-21T02:41:14.622671", "__class__": "BaseModel"}, "BaseModel.aa557e7b-c6b5-46d5-9041-fe130e21979e": {"id": "aa557e7b-c6b5-46d5-9041-fe130e21979e", "created_at": "2023-07-21T02:43:25.463788", "updated_at": "2023-07-21T02:43:25.464320", "__class__": "BaseModel"}, "User.bd9c4b7f-1e9b-46ea-864d-1a13ba7265a6": {"id": "bd9c4b7f-1e9b-46ea-864d-1a13ba7265a6", "created_at": "2023-07-21T03:08:53.990801", "updated_at": "2023-07-21T03:08:53.990801", "__class__": "User", "email": "", "password": "", "first_name": "", "last_name": ""}, "Place.203fa35d-7b47-403b-9db2-1c6d5e2358d1": {"id": "203fa35d-7b47-403b-9db2-1c6d5e2358d1", "created_at": "2023-07-21T03:09:00.021672", "updated_at": "2023-07-21T03:09:00.021672", "__class__": "Place", "city_id": "", "user_id": "", "name": "", "description": "", "number_rooms": 0, "number_bathrooms": 0, "max_guest": 0, "price_by_night": 0, "latitude": 0.0, "longitude": 0.0, "amenity_ids": []}, "Review.ddbff26a-656c-4fee-82dc-7d82e04a5ac8": {"id": "ddbff26a-656c-4fee-82dc-7d82e04a5ac8", "created_at": "2023-07-21T03:09:06.924108", "updated_at": "2023-07-21T03:09:06.924108", "__class__": "Review", "place_id": "", "user_id": "", "text": ""}, "State.282dc63c-7ede-4e34-836b-0b87e0f8234b": {"id": "282dc63c-7ede-4e34-836b-0b87e0f8234b", "created_at": "2023-07-21T03:09:14.648173", "updated_at": "2023-07-21T03:09:14.648173", "__class__": "State", "name": ""}, "City.90dc0530-a4e5-4cf1-ae6d-c73f5ab56e90": {"id": "90dc0530-a4e5-4cf1-ae6d-c73f5ab56e90", "created_at": "2023-07-21T03:09:18.969864", "updated_at": "2023-07-21T03:09:18.969864", "__class__": "City", "state_id": "", "name": ""}, "User.fff72873-290f-48e8-82c4-9a307d3ff35f": {"email": "json@me.com", "password": "", "first_name": "", "last_name": "", "id": "fff72873-290f-48e8-82c4-9a307d3ff35f", "created_at": "2023-07-21T21:35:15.155471", "updated_at": "2023-07-21T21:56:50.028476", "name": "Bernard", "__class__": "User"}, "User.6a924699-ccee-4b22-9cc4-68c5956d1ec6": {"id": "6a924699-ccee-4b22-9cc4-68c5956d1ec6", "created_at": "2023-07-21T21:35:52.230931", "updated_at": "2023-07-21T21:35:52.230931", "__class__": "User", "email": "", "password": "", "first_name": "", "last_name": ""}, "User.8a0b76d3-f6a5-4e04-9ec8-62b6990aa580": {"id": "8a0b76d3-f6a5-4e04-9ec8-62b6990aa580", "created_at": "2023-07-21T21:36:43.396766", "updated_at": "2023-07-21T21:36:43.396766", "__class__": "User", "email": "", "password": "", "first_name": "", "last_name": ""}, "User.f71e1b15-d840-4c78-bcea-c764d1906476": {"id": "f71e1b15-d840-4c78-bcea-c764d1906476", "created_at": "2023-07-21T21:37:43.693592", "updated_at": "2023-07-21T21:37:43.693592", "__class__": "User", "email": "", "password": "", "first_name": "", "last_name": ""}, "User.9126a870-cff5-46aa-a028-ed95809553c6": {"id": "9126a870-cff5-46aa-a028-ed95809553c6", "created_at": "2023-07-21T21:41:53.271585", "updated_at": "2023-07-21T21:41:53.271585", "__class__": "User", "email": "", "password": "", "first_name": "", "last_name": ""}, "User.172e7c61-68c6-420a-8250-dedfa89f2a9d": {"id": "172e7c61-68c6-420a-8250-dedfa89f2a9d", "created_at": "2023-07-21T21:45:47.233830", "updated_at": "2023-07-21T21:45:47.233830", "__class__": "User", "email": "", "password": "", "first_name": "", "last_name": ""}, "User.64d317a7-a1b4-4ac5-8ba0-cfc99f331550": {"id": "64d317a7-a1b4-4ac5-8ba0-cfc99f331550", "created_at": "2023-07-21T21:50:34.165410", "updated_at": "2023-07-21T21:50:34.165410", "__class__": "User", "email": "", "password": "", "first_name": "", "last_name": ""}, "User.1ab0802a-0e41-4b03-a0ea-42bd4a9d8916": {"email": "", "password": "", "first_name": "", "last_name": "", "id": "1ab0802a-0e41-4b03-a0ea-42bd4a9d8916", "created_at": "2023-07-21T21:56:50.028476", "updated_at": "2023-07-21T21:56:50.028476", "__class__": "User"}, "BaseModel.1193c237-bb91-463d-8de8-75903284b2a1": {"id": "1193c237-bb91-463d-8de8-75903284b2a1", "created_at": "2023-07-21T22:15:00.020865", "updated_at": "2023-07-21T22:15:00.020865", "__class__": "BaseModel"}, "BaseModel.57a206e8-81fb-4f71-b120-ae38d3497578": {"id": "57a206e8-81fb-4f71-b120-ae38d3497578", "created_at": "2023-07-21T22:22:46.272889", "updated_at": "2023-07-21T22:22:46.272889", "__class__": "BaseModel"}, "BaseModel.a63c68fa-febc-40d1-97a3-5143c75763a4": {"id": "a63c68fa-febc-40d1-97a3-5143c75763a4", "created_at": "2023-07-21T22:23:52.979624", "updated_at": "2023-07-21T22:23:52.979624", "__class__": "BaseModel"}, "Review.724f650e-ef85-4039-8af9-6696483dd026": {"place_id": "", "user_id": "", "text": "", "id": "724f650e-ef85-4039-8af9-6696483dd026", "created_at": "2023-07-21T22:55:46.841212", "updated_at": "2023-07-21T22:55:46.841212", "__class__": "Review"}, "Review.a83ae30b-5f92-4665-9386-7a365216e963": {"place_id": "", "user_id": "", "text": "", "id": "a83ae30b-5f92-4665-9386-7a365216e963", "created_at": "2023-07-21T22:55:46.841212", "updated_at": "2023-07-21T22:55:46.841212", "__class__": "Review"}, "Review.3ca23ba2-4d3b-4031-ae39-e528ca0d8fa3": {"place_id": "", "user_id": "", "text": "", "id": "3ca23ba2-4d3b-4031-ae39-e528ca0d8fa3", "created_at": "2023-07-21T22:55:46.841212", "updated_at": "2023-07-21T22:55:46.841212", "__class__": "Review"}, "Review.3bd3a82a-fb38-445c-980e-0e3abf06b863": {"place_id": "", "user_id": "", "text": "", "id": "3bd3a82a-fb38-445c-980e-0e3abf06b863", "created_at": "2023-07-21T22:55:46.841212", "updated_at": "2023-07-21T22:55:46.841212", "__class__": "Review"}, "Review.fb528018-71d9-43c7-b001-fcc16e927134": {"place_id": "", "user_id": "", "text": "", "id": "fb528018-71d9-43c7-b001-fcc16e927134", "created_at": "2023-07-21T22:55:46.841212", "updated_at": "2023-07-21T22:55:46.841212", "__class__": "Review"}, "Review.ea84f5e7-2319-4d0d-a018-cdf17cf2922f": {"place_id": "", "user_id": "", "text": "", "id": "ea84f5e7-2319-4d0d-a018-cdf17cf2922f", "created_at": "2023-07-21T22:55:46.841212", "updated_at": "2023-07-21T22:55:46.841212", "__class__": "Review"}, "Review.12b4c538-539a-413e-9813-3c141111d7a5": {"place_id": "", "user_id": "", "text": "", "id": "12b4c538-539a-413e-9813-3c141111d7a5", "created_at": "2023-07-21T22:55:46.841212", "updated_at": "2023-07-21T22:55:46.841212", "__class__": "Review"}, "Review.13aa6a4f-b06e-4e68-9856-386954a7241d": {"place_id": "", "user_id": "", "text": "", "id": "13aa6a4f-b06e-4e68-9856-386954a7241d", "created_at": "2023-07-21T22:55:46.841717", "updated_at": "2023-07-21T22:55:46.841717", "__class__": "Review"}, "Review.0e6e6fbe-aa41-4bdc-83e5-624d5f1c65d2": {"place_id": "", "user_id": "", "text": "", "id": "0e6e6fbe-aa41-4bdc-83e5-624d5f1c65d2", "created_at": "2023-07-21T22:55:46.841741", "updated_at": "2023-07-21T22:55:46.841741", "__class__": "Review"}, "Review.55b7609a-f454-4d39-b509-3cf33ccdf376": {"place_id": "", "user_id": "", "text": "", "id": "55b7609a-f454-4d39-b509-3cf33ccdf376", "created_at": "2023-07-21T22:55:46.841741", "updated_at": "2023-07-21T22:55:46.841741", "__class__": "Review"}, "Review.23c71203-542b-4b99-b8a3-29f3c59d9ee9": {"place_id": "", "user_id": "", "text": "", "id": "23c71203-542b-4b99-b8a3-29f3c59d9ee9", "created_at": "2023-07-21T22:55:46.841741", "updated_at": "2023-07-21T22:55:46.841741", "__class__": "Review"}, "Review.114d25b9-b56c-4c9d-9b10-ce1423d1f7c7": {"place_id": "", "user_id": "", "text": "", "id": "114d25b9-b56c-4c9d-9b10-ce1423d1f7c7", "created_at": "2023-07-21T22:55:46.841741", "updated_at": "2023-07-21T22:55:46.841741", "__class__": "Review"}, "Review.94392b7a-c17e-4eff-831d-61cab9a0a677": {"place_id": "", "user_id": "", "text": "", "id": "94392b7a-c17e-4eff-831d-61cab9a0a677", "created_at": "2023-07-21T22:55:46.841741", "updated_at": "2023-07-21T22:55:46.841741", "__class__": "Review"}, "Review.a83899dd-f883-40b5-905b-a1bc9e9fc17f": {"place_id": "", "user_id": "", "text": "", "id": "a83899dd-f883-40b5-905b-a1bc9e9fc17f", "created_at": "2023-07-21T22:55:46.841741", "updated_at": "2023-07-21T22:55:46.841741", "__class__": "Review"}, "Review.f4be61df-4c23-4812-9b97-80cb0485a0b2": {"place_id": "", "user_id": "", "text": "", "id": "f4be61df-4c23-4812-9b97-80cb0485a0b2", "created_at": "2023-07-21T22:55:46.841741", "updated_at": "2023-07-21T22:55:46.841741", "__class__": "Review"}, "Review.6dcff84c-95cc-48e5-8ecf-0098f96334f1": {"place_id": "", "user_id": "", "text": "", "id": "6dcff84c-95cc-48e5-8ecf-0098f96334f1", "created_at": "2023-07-21T22:55:46.841741", "updated_at": "2023-07-21T22:55:46.841741", "__class__": "Review"}, "Review.aad3d2cb-7a0e-439f-afa9-10679e8178e6": {"place_id": "", "user_id": "", "text": "", "id": "aad3d2cb-7a0e-439f-afa9-10679e8178e6", "created_at": "2023-07-21T22:55:46.841741", "updated_at": "2023-07-21T22:55:46.841741", "__class__": "Review"}, "Review.f0cbd8de-dd85-4cf1-a3c9-239b2e3f3233": {"place_id": "", "user_id": "", "text": "", "id": "f0cbd8de-dd85-4cf1-a3c9-239b2e3f3233", "created_at": "2023-07-21T22:55:46.841741", "updated_at": "2023-07-21T22:55:46.841741", "__class__": "Review"}, "Review.de770036-3cdf-4f17-b288-a6d3ad3dbc6b": {"place_id": "", "user_id": "", "text": "", "id": "de770036-3cdf-4f17-b288-a6d3ad3dbc6b", "created_at": "2023-07-21T22:55:46.841741", "updated_at": "2023-07-21T22:55:46.841741", "__class__": "Review"}, "Review.ea8fd775-76b2-4a29-901c-5ac8f75598a0": {"place_id": "", "user_id": "", "text": "", "id": "ea8fd775-76b2-4a29-901c-5ac8f75598a0", "created_at": "2023-07-21T22:56:12.813345", "updated_at": "2023-07-21T22:56:12.813345", "__class__": "Review"}, "Review.e146b5fd-62ff-45b0-a21a-4a08a00ee92f": {"place_id": "", "user_id": "", "text": "", "id": "e146b5fd-62ff-45b0-a21a-4a08a00ee92f", "created_at": "2023-07-21T22:56:15.506852", "updated_at": "2023-07-21T22:56:15.506852", "__class__": "Review"}, "Review.14386fa9-20a3-4e58-9bc2-e0331fd5d29b": {"place_id": "", "user_id": "", "text": "", "id": "14386fa9-20a3-4e58-9bc2-e0331fd5d29b", "created_at": "2023-07-21T22:56:16.425542", "updated_at": "2023-07-21T22:56:16.425542", "__class__": "Review"}, "Review.3f3440b9-8856-41f9-8eeb-2c5244ef8a46": {"place_id": "", "user_id": "", "text": "", "id": "3f3440b9-8856-41f9-8eeb-2c5244ef8a46", "created_at": "2023-07-21T22:56:16.686958", "updated_at": "2023-07-21T22:56:16.686958", "__class__": "Review"}, "Review.7313a6d4-1658-4bd8-bae4-ab4cca0e4e02": {"place_id": "", "user_id": "", "text": "", "id": "7313a6d4-1658-4bd8-bae4-ab4cca0e4e02", "created_at": "2023-07-21T22:56:16.947060", "updated_at": "2023-07-21T22:56:16.947060", "__class__": "Review"}, "Review.db7e1ab4-ea27-491b-8528-b5f02d8e37f8": {"place_id": "", "user_id": "", "text": "", "id": "db7e1ab4-ea27-491b-8528-b5f02d8e37f8", "created_at": "2023-07-21T22:56:17.198696", "updated_at": "2023-07-21T22:56:17.198696", "__class__": "Review"}, "Review.a590340b-c9eb-4eb4-8a7a-3499fe1504c8": {"place_id": "", "user_id": "", "text": "", "id": "a590340b-c9eb-4eb4-8a7a-3499fe1504c8", "created_at": "2023-07-21T22:56:17.455171", "updated_at": "2023-07-21T22:56:17.455171", "__class__": "Review"}, "Review.9f51a145-a9c9-4c33-b5c4-7de03f0c3d28": {"place_id": "", "user_id": "", "text": "", "id": "9f51a145-a9c9-4c33-b5c4-7de03f0c3d28", "created_at": "2023-07-21T22:56:17.712457", "updated_at": "2023-07-21T22:56:17.712457", "__class__": "Review"}, "Review.7e1a5210-80e0-4cc9-b7ff-f2a4985b3f56": {"place_id": "", "user_id": "", "text": "", "id": "7e1a5210-80e0-4cc9-b7ff-f2a4985b3f56", "created_at": "2023-07-21T22:56:17.953307", "updated_at": "2023-07-21T22:56:17.953307", "__class__": "Review"}, "Review.0298e564-c163-4a9f-a5e1-d3223d5764c3": {"place_id": "", "user_id": "", "text": "", "id": "0298e564-c163-4a9f-a5e1-d3223d5764c3", "created_at": "2023-07-21T22:56:18.202910", "updated_at": "2023-07-21T22:56:18.202910", "__class__": "Review"}, "Review.d451a703-d3fd-4789-b518-bdddc9cd9b2c": {"place_id": "", "user_id": "", "text": "", "id": "d451a703-d3fd-4789-b518-bdddc9cd9b2c", "created_at": "2023-07-21T22:56:18.443589", "updated_at": "2023-07-21T22:56:18.443589", "__class__": "Review"}, "Review.7eed12b4-0825-4caf-9466-1d03d526ce2c": {"place_id": "", "user_id": "", "text": "", "id": "7eed12b4-0825-4caf-9466-1d03d526ce2c", "created_at": "2023-07-21T22:56:18.690587", "updated_at": "2023-07-21T22:56:18.690587", "__class__": "Review"}, "Review.69254ba5-7da2-4539-b9b2-70e843879727": {"place_id": "", "user_id": "", "text": "", "id": "69254ba5-7da2-4539-b9b2-70e843879727", "created_at": "2023-07-21T22:56:18.941888", "updated_at": "2023-07-21T22:56:18.942424", "__class__": "Review"}, "Review.d0ea1e60-20e9-4538-839f-d666082bb83e": {"place_id": "", "user_id": "", "text": "", "id": "d0ea1e60-20e9-4538-839f-d666082bb83e", "created_at": "2023-07-21T22:56:19.188489", "updated_at": "2023-07-21T22:56:19.188489", "__class__": "Review"}, "Review.f8e79fac-72c5-4e48-aa9a-3645a08bc9ed": {"place_id": "", "user_id": "", "text": "", "id": "f8e79fac-72c5-4e48-aa9a-3645a08bc9ed", "created_at": "2023-07-21T22:56:19.444517", "updated_at": "2023-07-21T22:56:19.444517", "__class__": "Review"}, "Review.4c59afce-97c4-4908-8ce1-616b1fc53f48": {"place_id": "", "user_id": "", "text": "", "id": "4c59afce-97c4-4908-8ce1-616b1fc53f48", "created_at": "2023-07-21T22:56:19.698910", "updated_at": "2023-07-21T22:56:19.698910", "__class__": "Review"}, "Review.c97147aa-447e-4606-a17b-fea7dacb9a4c": {"place_id": "", "user_id": "", "text": "", "id": "c97147aa-447e-4606-a17b-fea7dacb9a4c", "created_at": "2023-07-21T22:56:21.365280", "updated_at": "2023-07-21T22:56:21.365280", "__class__": "Review"}, "User.3874b6c2-9917-4115-9dbd-3fc27c9b3d5b": {"email": "", "password": "", "first_name": "John", "last_name": "", "id": "3874b6c2-9917-4115-9dbd-3fc27c9b3d5b", "created_at": "2023-07-21T23:00:10.580081", "updated_at": "2023-07-21T23:17:12.104644", "age": "89", "__class__": "User"}, "User.ba9e2575-f5fc-471a-bc75-ce155833bbb5": {"email": "", "password": "", "first_name": "", "last_name": "", "id": "ba9e2575-f5fc-471a-bc75-ce155833bbb5", "created_at": "2023-07-21T23:15:34.249508", "updated_at": "2023-07-21T23:15:34.249508", "__class__": "User"}, "User.ef6306fd-cbfa-4f11-a252-2d8a9fc83ef0": {"email": "", "password": "", "first_name": "", "last_name": "", "id": "ef6306fd-cbfa-4f11-a252-2d8a9fc83ef0", "created_at": "2023-07-21T23:16:21.149189", "updated_at": "2023-07-21T23:16:21.149189", "__class__": "User"}, "User.06908899-bd68-40d8-8b75-914c5cebf5ab": {"email": "", "password": "", "first_name": "", "last_name": "", "id": "06908899-bd68-40d8-8b75-914c5cebf5ab", "created_at": "2023-07-21T23:17:12.104116", "updated_at": "2023-07-21T23:17:12.104116", "__class__": "User"}, "User.7b7f42bf-85a4-4282-8477-e2d9e7b686f2": {"email": "", "password": "", "first_name": "", "last_name": "", "id": "7b7f42bf-85a4-4282-8477-e2d9e7b686f2", "created_at": "2023-07-21T23:34:59.747649", "updated_at": "2023-07-21T23:35:43.223189", "'first_name'": "John", "age": "89", "__class__": "User"}, "User.8d6e0786-94ff-4a11-8023-d3b4842593dc": {"email": "", "password": "", "first_name": "", "last_name": "", "id": "8d6e0786-94ff-4a11-8023-d3b4842593dc", "created_at": "2023-07-21T23:35:43.223189", "updated_at": "2023-07-21T23:35:43.223189", "__class__": "User"}}